tabby_payment/__init__.py
tabby_payment/forms.py
tabby_payment/urls.py
tabby_payment/views.py
tabby_payment/commerce/__init__.py
tabby_payment/commerce/checkout.py
tabby_payment/commerce/dummy.py
tabby_payment/commerce/enums.py
tabby_payment/templates/tabby-extension-redirect-form.html
tabby_payment/tests/__init__.py
tabby_payment/tests/mixins.py
tabby_payment/tests/test_service.py
tabby_payment/tests/test_views.py
tabby_payment-1.1.0.dist-info/METADATA
tabby_payment-1.1.0.dist-info/WHEEL
tabby_payment-1.1.0.dist-info/top_level.txt
tabby_payment-1.1.0.dist-info/RECORD
