Metadata-Version: 2.2
Name: tabby-payment
Version: 1.1.0
Summary: A common library for provide payment gateway for Tabby Payment.
Home-page: https://bitbucket.org/akinonteam/tabby-payment
Author: Akinon
Author-email: dev@akinon.com
Requires-Dist: Django<4.0,>=2.2.9
Requires-Dist: requests
Requires-Dist: djangorestframework<3.15,>=3.11.0
Requires-Dist: orjson==3.10.3
Requires-Dist: requests-mock==1.8.0
Requires-Dist: mock==4.0.3
Dynamic: author
Dynamic: author-email
Dynamic: description
Dynamic: description-content-type
Dynamic: home-page
Dynamic: requires-dist
Dynamic: summary
